<annotation>
  <folder>images</folder>
  <filename>resize_image23</filename>
  <path>C:\Users\MELISSA\Downloads\Experiment_2\images\resize_image23.jpg</path>
  <source>
    <database>Unknown</database>
  </source>
  <size>
    <width>509</width>
    <height>405</height>
    <depth>3</depth>
  </size>
  <segmented>0</segmented>
  <object>
    <name>eye</name>
    <pose>Unspecified</pose>
    <truncated>0</truncated>
    <difficult>0</difficult>
    <bndbox>
      <xmin>231</xmin>
      <ymin>121</ymin>
      <xmax>294</xmax>
      <ymax>155</ymax>
    </bndbox>
  </object>
  <object>
    <name>eye</name>
    <pose>Unspecified</pose>
    <truncated>0</truncated>
    <difficult>0</difficult>
    <bndbox>
      <xmin>342</xmin>
      <ymin>141</ymin>
      <xmax>382</xmax>
      <ymax>174</ymax>
    </bndbox>
  </object>
  <object>
    <name>nose</name>
    <pose>Unspecified</pose>
    <truncated>0</truncated>
    <difficult>0</difficult>
    <bndbox>
      <xmin>295</xmin>
      <ymin>174</ymin>
      <xmax>357</xmax>
      <ymax>220</ymax>
    </bndbox>
  </object>
  <object>
    <name>mouth</name>
    <pose>Unspecified</pose>
    <truncated>0</truncated>
    <difficult>0</difficult>
    <bndbox>
      <xmin>267</xmin>
      <ymin>233</ymin>
      <xmax>357</xmax>
      <ymax>284</ymax>
    </bndbox>
  </object>
</annotation>
